{
    "start_date": "2023-09-07T00:00:00+00:00",
    "end_date": "2025-08-06T23:00:00+00:00",
    "horizon": 168,
    "features": [
        "temperature_2m_city_paris",
        "relative_humidity_2m_city_paris",
        "surface_pressure_city_paris",
        "precipitation_city_paris",
        "cloud_cover_city_paris",
        "HDH_city_paris",
        "CDH_city_paris",
        "humidex_city_paris",
        "pressure_trend_city_paris",
        "rain_indicator_city_paris",
        "temp_lag_1_city_paris",
        "temp_lag_3_city_paris",
        "precip_lags_lag_1_city_paris",
        "precip_lags_lag_3_city_paris",
        "precip_lags_lag_6_city_paris",
        "cloud_lags_lag_1_city_paris",
        "cloud_lags_lag_3_city_paris",
        "cloud_lags_lag_6_city_paris",
        "temp_roll_6_city_paris",
        "temp_roll_12_city_paris",
        "temp_roll_24_city_paris",
        "temperature_2m_city_marseille",
        "relative_humidity_2m_city_marseille",
        "surface_pressure_city_marseille",
        "precipitation_city_marseille",
        "cloud_cover_city_marseille",
        "HDH_city_marseille",
        "CDH_city_marseille",
        "humidex_city_marseille",
        "pressure_trend_city_marseille",
        "rain_indicator_city_marseille",
        "temp_lag_1_city_marseille",
        "temp_lag_3_city_marseille",
        "precip_lags_lag_1_city_marseille",
        "precip_lags_lag_3_city_marseille",
        "precip_lags_lag_6_city_marseille",
        "cloud_lags_lag_1_city_marseille",
        "cloud_lags_lag_3_city_marseille",
        "cloud_lags_lag_6_city_marseille",
        "temp_roll_6_city_marseille",
        "temp_roll_12_city_marseille",
        "temp_roll_24_city_marseille",
        "temperature_2m_city_lyon",
        "relative_humidity_2m_city_lyon",
        "surface_pressure_city_lyon",
        "precipitation_city_lyon",
        "cloud_cover_city_lyon",
        "HDH_city_lyon",
        "CDH_city_lyon",
        "humidex_city_lyon",
        "pressure_trend_city_lyon",
        "rain_indicator_city_lyon",
        "temp_lag_1_city_lyon",
        "temp_lag_3_city_lyon",
        "precip_lags_lag_1_city_lyon",
        "precip_lags_lag_3_city_lyon",
        "precip_lags_lag_6_city_lyon",
        "cloud_lags_lag_1_city_lyon",
        "cloud_lags_lag_3_city_lyon",
        "cloud_lags_lag_6_city_lyon",
        "temp_roll_6_city_lyon",
        "temp_roll_12_city_lyon",
        "temp_roll_24_city_lyon",
        "temperature_2m_city_toulouse",
        "relative_humidity_2m_city_toulouse",
        "surface_pressure_city_toulouse",
        "precipitation_city_toulouse",
        "cloud_cover_city_toulouse",
        "HDH_city_toulouse",
        "CDH_city_toulouse",
        "humidex_city_toulouse",
        "pressure_trend_city_toulouse",
        "rain_indicator_city_toulouse",
        "temp_lag_1_city_toulouse",
        "temp_lag_3_city_toulouse",
        "precip_lags_lag_1_city_toulouse",
        "precip_lags_lag_3_city_toulouse",
        "precip_lags_lag_6_city_toulouse",
        "cloud_lags_lag_1_city_toulouse",
        "cloud_lags_lag_3_city_toulouse",
        "cloud_lags_lag_6_city_toulouse",
        "temp_roll_6_city_toulouse",
        "temp_roll_12_city_toulouse",
        "temp_roll_24_city_toulouse",
        "temperature_2m_city_lille",
        "relative_humidity_2m_city_lille",
        "surface_pressure_city_lille",
        "precipitation_city_lille",
        "cloud_cover_city_lille",
        "HDH_city_lille",
        "CDH_city_lille",
        "humidex_city_lille",
        "pressure_trend_city_lille",
        "rain_indicator_city_lille",
        "temp_lag_1_city_lille",
        "temp_lag_3_city_lille",
        "precip_lags_lag_1_city_lille",
        "precip_lags_lag_3_city_lille",
        "precip_lags_lag_6_city_lille",
        "cloud_lags_lag_1_city_lille",
        "cloud_lags_lag_3_city_lille",
        "cloud_lags_lag_6_city_lille",
        "temp_roll_6_city_lille",
        "temp_roll_12_city_lille",
        "temp_roll_24_city_lille",
        "wind_offshore_rte",
        "wind_onshore_rte",
        "solar_rte",
        "hour",
        "dayofweek",
        "is_holiday",
        "hour_sin",
        "hour_cos",
        "day_sin",
        "day_cos"
    ],
    "error_metrics": {
        "2025-07-03T00:00:00+00:00": {
            "load_rte": {
                "mse": 9254718.350900378,
                "rmse": 3042.156858365521,
                "mae": 2525.454659598214,
                "mape": 5.650714043769088,
                "smape": 11.771332163267347,
                "bias": -2521.158621651786,
                "variance": 2898477.5553712454,
                "std": 1702.4915727753971,
                "r2": 0.6631698794880263,
                "prediction_interval_coverage": 0.09523809523809523,
                "prediction_interval_width": 1115.9998989969524
            }
        },
        "2025-07-10T00:00:00+00:00": {
            "load_rte": {
                "mse": 5060662.757517723,
                "rmse": 2249.59168684402,
                "mae": 1741.7824125744048,
                "mape": 4.001903888721875,
                "smape": 8.108679337103014,
                "bias": -819.9932570684524,
                "variance": 4388273.815879996,
                "std": 2094.8207121087944,
                "r2": 0.8078589137274098,
                "prediction_interval_coverage": 0.2261904761904762,
                "prediction_interval_width": 1115.9998989969524
            }
        },
        "2025-07-17T00:00:00+00:00": {
            "load_rte": {
                "mse": 2635287.5450528916,
                "rmse": 1623.3568754444882,
                "mae": 1244.547828311012,
                "mape": 2.8691716594264083,
                "smape": 5.8615013485020695,
                "bias": -951.4889555431548,
                "variance": 1729956.312532288,
                "std": 1315.2780362084238,
                "r2": 0.9011315310888521,
                "prediction_interval_coverage": 0.3333333333333333,
                "prediction_interval_width": 1115.9998989969529
            }
        },
        "2025-07-24T00:00:00+00:00": {
            "load_rte": {
                "mse": 1055986.5640534447,
                "rmse": 1027.6120688535361,
                "mae": 787.6010044642857,
                "mape": 1.9236329457205943,
                "smape": 3.8593383509563948,
                "bias": -83.70061383928571,
                "variance": 1048980.7712963712,
                "std": 1024.1976231647734,
                "r2": 0.9520797966421408,
                "prediction_interval_coverage": 0.4226190476190476,
                "prediction_interval_width": 1115.9998989969524
            }
        },
        "2025-07-31T00:00:00+00:00": {
            "load_rte": {
                "mse": 7219840.886972904,
                "rmse": 2686.97616047722,
                "mae": 2185.0628603980654,
                "mape": 5.494809630573004,
                "smape": 10.57069856745818,
                "bias": 2080.2256208147323,
                "variance": 2892502.2534788665,
                "std": 1700.7357976707806,
                "r2": 0.6244296568202619,
                "prediction_interval_coverage": 0.18452380952380953,
                "prediction_interval_width": 1115.9998989969524
            }
        }
    }
}