{
    "start_date": "2023-10-31T00:00:00+00:00",
    "end_date": "2025-09-22T23:00:00+00:00",
    "horizon": 168,
    "features": [
        "temperature_2m_agg",
        "relative_humidity_2m_agg",
        "surface_pressure_agg",
        "precipitation_agg",
        "cloud_cover_agg",
        "HDH_agg",
        "CDH_agg",
        "temp_gradient_agg",
        "humidex_agg",
        "pressure_trend_agg",
        "rain_indicator_agg",
        "wind_speed_gradient_agg",
        "cloud_cover_fraction_agg",
        "effective_solar_agg",
        "temp_lag_1_agg",
        "temp_lag_3_agg",
        "cloud_lags_lag_1_agg",
        "cloud_lags_lag_3_agg",
        "cloud_lags_lag_6_agg",
        "temp_roll_3_agg",
        "temp_roll_6_agg",
        "wind_offshore_50hz",
        "wind_offshore_tenn",
        "wind_onshore_ampr",
        "wind_onshore_50hz",
        "wind_onshore_tenn",
        "wind_onshore_tran",
        "solar_ampr",
        "solar_50hz",
        "solar_tenn",
        "solar_tran",
        "hour",
        "dayofweek",
        "is_holiday",
        "hour_sin",
        "hour_cos",
        "day_sin",
        "day_cos",
        "load_ampr_lag_1",
        "load_ampr_lag_2",
        "load_ampr_lag_3",
        "load_ampr_lag_4",
        "load_ampr_lag_5",
        "load_ampr_lag_6",
        "load_ampr_lag_7",
        "load_ampr_lag_8",
        "load_ampr_lag_9",
        "load_ampr_lag_10",
        "load_ampr_lag_11",
        "load_ampr_lag_12"
    ],
    "error_metrics": {
        "2025-08-19T00:00:00+00:00": {
            "load_ampr": {
                "mse": 1704419.141152151,
                "rmse": 1305.5340444247906,
                "mae": 1071.5355448997154,
                "mape": 6.0609399758620155,
                "smape": 12.486788053918449,
                "bias": -620.2910499340918,
                "variance": 1319658.1545238127,
                "std": 1148.7637505265443,
                "r2": 0.7304828113014858,
                "prediction_interval_coverage": 0.5119047619047619,
                "prediction_interval_width": 1870.133428109641
            }
        },
        "2025-08-26T00:00:00+00:00": {
            "load_ampr": {
                "mse": 1323939.6784645703,
                "rmse": 1150.6257768990622,
                "mae": 932.045105690403,
                "mape": 5.0714884561000355,
                "smape": 10.445131406300948,
                "bias": -647.1519037745659,
                "variance": 905134.0919055255,
                "std": 951.3853540524605,
                "r2": 0.8231679154319846,
                "prediction_interval_coverage": 0.5357142857142857,
                "prediction_interval_width": 1869.8049101527195
            }
        },
        "2025-09-02T00:00:00+00:00": {
            "load_ampr": {
                "mse": 1869932.5866381486,
                "rmse": 1367.454784129314,
                "mae": 1117.7247394091808,
                "mape": 6.114773484142092,
                "smape": 12.750844921011279,
                "bias": -927.4890420222672,
                "variance": 1009696.6635667655,
                "std": 1004.8366352630488,
                "r2": 0.7902391715549518,
                "prediction_interval_coverage": 0.4642857142857143,
                "prediction_interval_width": 1870.2223364451243
            }
        },
        "2025-09-09T00:00:00+00:00": {
            "load_ampr": {
                "mse": 1691868.4356309671,
                "rmse": 1300.7184305724923,
                "mae": 1049.1487218488085,
                "mape": 5.837295988382207,
                "smape": 11.982050385205403,
                "bias": -579.2697753273045,
                "variance": 1356314.9630232214,
                "std": 1164.6093606970628,
                "r2": 0.8040052137413016,
                "prediction_interval_coverage": 0.47619047619047616,
                "prediction_interval_width": 1870.2185036005692
            }
        },
        "2025-09-16T00:00:00+00:00": {
            "load_ampr": {
                "mse": 1611528.7098931202,
                "rmse": 1269.4600072050794,
                "mae": 1044.0898231939584,
                "mape": 5.83196786621715,
                "smape": 11.61734410805638,
                "bias": -191.2148652886815,
                "variance": 1574965.585185752,
                "std": 1254.9763285360214,
                "r2": 0.8268923193111783,
                "prediction_interval_coverage": 0.5357142857142857,
                "prediction_interval_width": 1869.5808086432687
            }
        }
    }
}