{
    "start_date": "2023-07-29T00:00:00+00:00",
    "end_date": "2025-06-27T23:00:00+00:00",
    "horizon": 168,
    "features": [
        "temperature_2m_agg",
        "relative_humidity_2m_agg",
        "surface_pressure_agg",
        "precipitation_agg",
        "cloud_cover_agg",
        "global_tilted_ratio_agg",
        "precip_lag_1_agg",
        "precip_lag_6_agg",
        "solar_elevation_deg_sol_ernsthof",
        "solar_azimuth_deg_sol_ernsthof",
        "solar_elevation_deg_sol_erbach",
        "solar_azimuth_deg_sol_erbach",
        "solar_elevation_deg_sol_aalen",
        "solar_azimuth_deg_sol_aalen",
        "hour",
        "dayofweek",
        "is_holiday",
        "hour_sin",
        "hour_cos",
        "day_sin",
        "day_cos"
    ],
    "error_metrics": {
        "2025-05-24T00:00:00+00:00": {
            "solar_tran": {
                "mse": 284970.04866092704,
                "rmse": 533.8258598653001,
                "mae": 288.7798317716945,
                "mape": 4345138338824.9946,
                "smape": 167.23700987143627,
                "bias": -132.71308203077032,
                "variance": 267357.286518821,
                "std": 517.0660369032383,
                "r2": 0.9064139174068311,
                "prediction_interval_coverage": 0.7202380952380952,
                "prediction_interval_width": 700.5113020677228
            }
        },
        "2025-05-31T00:00:00+00:00": {
            "solar_tran": {
                "mse": 250636.52224922282,
                "rmse": 500.6361176036172,
                "mae": 267.41796817701487,
                "mape": 3391015684031.9673,
                "smape": 161.53009754350686,
                "bias": -99.66243885351079,
                "variance": 240703.92053099308,
                "std": 490.6158584177575,
                "r2": 0.9092681434325722,
                "prediction_interval_coverage": 0.7321428571428571,
                "prediction_interval_width": 700.5113020677227
            }
        },
        "2025-06-07T00:00:00+00:00": {
            "solar_tran": {
                "mse": 215686.43466155106,
                "rmse": 464.4205364338996,
                "mae": 297.2550999042061,
                "mape": 3814313839636.377,
                "smape": 157.44908017694098,
                "bias": -190.17107199132442,
                "variance": 179521.39803922156,
                "std": 423.6996554627128,
                "r2": 0.9472920917634347,
                "prediction_interval_coverage": 0.6369047619047619,
                "prediction_interval_width": 700.5113020677229
            }
        },
        "2025-06-14T00:00:00+00:00": {
            "solar_tran": {
                "mse": 241694.1379971803,
                "rmse": 491.623980291015,
                "mae": 329.98118690579264,
                "mape": 7856013615278.513,
                "smape": 156.55955051342468,
                "bias": -207.1847694685982,
                "variance": 198768.60929742412,
                "std": 445.8347331662531,
                "r2": 0.9460248932904028,
                "prediction_interval_coverage": 0.6011904761904762,
                "prediction_interval_width": 700.5113020677229
            }
        },
        "2025-06-21T00:00:00+00:00": {
            "solar_tran": {
                "mse": 242797.62257316336,
                "rmse": 492.74498736482684,
                "mae": 317.54041234261933,
                "mape": 6083744750168.654,
                "smape": 159.42811684517392,
                "bias": -261.97354691262757,
                "variance": 174167.4832911807,
                "std": 417.33377923573437,
                "r2": 0.9405559673897147,
                "prediction_interval_coverage": 0.625,
                "prediction_interval_width": 700.5113020677229
            }
        }
    }
}