{
    "start_date": "2023-06-21T00:00:00+00:00",
    "end_date": "2025-05-20T23:00:00+00:00",
    "horizon": 168,
    "features": [
        "temperature_2m_agg",
        "relative_humidity_2m_agg",
        "surface_pressure_agg",
        "precipitation_agg",
        "cloud_cover_agg",
        "wind_speed_10m_agg",
        "wind_speed_100m_agg",
        "wind_direction_10m_agg",
        "wind_gusts_10m_agg",
        "air_density_agg",
        "wind_power_density_agg",
        "wind_dir_sin_agg",
        "wind_dir_cos_agg",
        "dew_point_temperature_agg",
        "vapor_pressure_agg",
        "hour",
        "dayofweek",
        "is_holiday",
        "hour_sin",
        "hour_cos",
        "day_sin",
        "day_cos"
    ],
    "error_metrics": {
        "2025-04-16T00:00:00+00:00": {
            "wind_offshore_rte": {
                "mse": 48514.354008428265,
                "rmse": 220.2597421419272,
                "mae": 158.3491850243438,
                "mape": 108.00974724153932,
                "smape": 99.13142197330777,
                "bias": -98.27307282210816,
                "variance": 38856.757166528885,
                "std": 197.1211738158255,
                "r2": 0.6373209293448843,
                "prediction_interval_coverage": 0.6488095238095238,
                "prediction_interval_width": 286.32173771664975
            }
        },
        "2025-04-23T00:00:00+00:00": {
            "wind_offshore_rte": {
                "mse": 75518.51092754364,
                "rmse": 274.8063152977814,
                "mae": 203.45250904749312,
                "mape": 1222.4758286761062,
                "smape": 129.7097422502684,
                "bias": -34.649687418861994,
                "variance": 74317.9100893188,
                "std": 272.6131143017863,
                "r2": 0.4625729301908358,
                "prediction_interval_coverage": 0.47023809523809523,
                "prediction_interval_width": 286.32173771664975
            }
        },
        "2025-04-30T00:00:00+00:00": {
            "wind_offshore_rte": {
                "mse": 129319.01567498298,
                "rmse": 359.6095322359837,
                "mae": 281.1498133227939,
                "mape": 51.935119866701186,
                "smape": 110.36714989004875,
                "bias": -251.42936096872603,
                "variance": 66102.29211784103,
                "std": 257.1036602575721,
                "r2": 0.1910836875036428,
                "prediction_interval_coverage": 0.375,
                "prediction_interval_width": 286.32173771664975
            }
        },
        "2025-05-07T00:00:00+00:00": {
            "wind_offshore_rte": {
                "mse": 34681.797773837985,
                "rmse": 186.23049635824415,
                "mae": 146.371158128693,
                "mape": 74.60683916959131,
                "smape": 119.19118236886692,
                "bias": -108.59775241783687,
                "variance": 22888.325943632197,
                "std": 151.28888241913944,
                "r2": 0.5347625764374278,
                "prediction_interval_coverage": 0.5595238095238095,
                "prediction_interval_width": 286.32173771664975
            }
        },
        "2025-05-14T00:00:00+00:00": {
            "wind_offshore_rte": {
                "mse": 45949.3164732969,
                "rmse": 214.35791674975968,
                "mae": 151.35838890075684,
                "mape": 47.570958947593766,
                "smape": 86.74610674130837,
                "bias": -88.6307834443592,
                "variance": 38093.900699336016,
                "std": 195.17658850214596,
                "r2": 0.36161762499831795,
                "prediction_interval_coverage": 0.6428571428571429,
                "prediction_interval_width": 286.32173771664975
            }
        }
    }
}