{
    "start_date": "2023-04-30T00:00:00+00:00",
    "end_date": "2025-03-22T23:00:00+00:00",
    "horizon": 168,
    "features": [
        "relative_humidity_2m_agg",
        "wind_speed_10m_agg",
        "wind_speed_100m_agg",
        "wind_direction_10m_agg",
        "wind_direction_100m_agg",
        "wind_gusts_10m_agg",
        "wind_shear_agg",
        "gust_factor_agg",
        "wind_speed_lag_1_agg",
        "wind_speed_lag_6_agg",
        "wind_speed_lag_12_agg",
        "precip_lag_1_agg",
        "precip_lag_6_agg",
        "hour",
        "dayofweek",
        "is_holiday",
        "hour_sin",
        "hour_cos",
        "day_sin",
        "day_cos",
        "wind_offshore_rte_lag_1"
    ],
    "error_metrics": {
        "2025-02-16T00:00:00+00:00": {
            "wind_offshore_rte": {
                "mse": 71268.01329596998,
                "rmse": 266.9606961632554,
                "mae": 202.7284273744395,
                "mape": 30.351037093108204,
                "smape": 61.51520180522674,
                "bias": -153.04440432984345,
                "variance": 47845.423599293375,
                "std": 218.73596777689164,
                "r2": 0.6183737519122003,
                "prediction_interval_coverage": 0.39880952380952384,
                "prediction_interval_width": 191.1188464676849
            }
        },
        "2025-02-23T00:00:00+00:00": {
            "wind_offshore_rte": {
                "mse": 135002.09695339977,
                "rmse": 367.42631499853104,
                "mae": 275.17303019501134,
                "mape": 31.76490257623502,
                "smape": 73.92222575070744,
                "bias": -249.6772072400518,
                "variance": 72663.38913820799,
                "std": 269.56147561958477,
                "r2": 0.1715978330441862,
                "prediction_interval_coverage": 0.34523809523809523,
                "prediction_interval_width": 191.1188464676849
            }
        },
        "2025-03-02T00:00:00+00:00": {
            "wind_offshore_rte": {
                "mse": 59355.829122484254,
                "rmse": 243.6305176337403,
                "mae": 183.93705417747506,
                "mape": 52.16641770048172,
                "smape": 77.38741833916283,
                "bias": -98.4035754650278,
                "variance": 49672.565458182835,
                "std": 222.8734292332373,
                "r2": 0.6773548548669801,
                "prediction_interval_coverage": 0.3869047619047619,
                "prediction_interval_width": 191.1188464676849
            }
        },
        "2025-03-09T00:00:00+00:00": {
            "wind_offshore_rte": {
                "mse": 83482.08477220536,
                "rmse": 288.9326647719246,
                "mae": 213.04830806576436,
                "mape": 156.9277051188934,
                "smape": 116.5608069966188,
                "bias": -116.92831340604029,
                "variance": 69809.85429622418,
                "std": 264.2155451449142,
                "r2": 0.42401320192514547,
                "prediction_interval_coverage": 0.39880952380952384,
                "prediction_interval_width": 191.1188464676849
            }
        },
        "2025-03-16T00:00:00+00:00": {
            "wind_offshore_rte": {
                "mse": 78576.83226841845,
                "rmse": 280.315594051452,
                "mae": 226.36046397778938,
                "mape": 37.9109455551979,
                "smape": 66.16962879243327,
                "bias": -194.11416681245777,
                "variance": 40896.52251112378,
                "std": 202.22888644089346,
                "r2": 0.13716238554244375,
                "prediction_interval_coverage": 0.27380952380952384,
                "prediction_interval_width": 191.1188464676849
            }
        }
    }
}