{
    "start_date": "2024-01-31T00:00:00+00:00",
    "end_date": "2025-12-30T23:00:00+00:00",
    "horizon": 168,
    "features": [
        "temperature_2m_agg",
        "relative_humidity_2m_agg",
        "surface_pressure_agg",
        "precipitation_agg",
        "cloud_cover_agg",
        "shortwave_radiation_agg",
        "direct_radiation_agg",
        "diffuse_radiation_agg",
        "direct_normal_irradiance_agg",
        "global_tilted_irradiance_agg",
        "terrestrial_radiation_agg",
        "cloud_cover_fraction_agg",
        "clear_sky_fraction_agg",
        "diffuse_ratio_agg",
        "dni_ratio_agg",
        "dew_point_temperature_agg",
        "precip_lag_1_agg",
        "precip_lag_6_agg",
        "precip_lag_12_agg",
        "precip_lag_24_agg",
        "cloud_lag_1_agg",
        "cloud_lag_3_agg",
        "cloud_lag_6_agg",
        "cloud_lag_12_agg",
        "shortwave_lag_1_agg",
        "shortwave_lag_3_agg",
        "shortwave_lag_6_agg",
        "shortwave_lag_12_agg",
        "solar_elevation_deg_sol_witznitz",
        "solar_azimuth_deg_sol_witznitz",
        "solar_elevation_deg_sol_weesow",
        "solar_azimuth_deg_sol_weesow",
        "solar_elevation_deg_sol_meuro",
        "solar_azimuth_deg_sol_meuro",
        "solar_elevation_deg_sol_gottesgabe",
        "solar_azimuth_deg_sol_gottesgabe",
        "hour",
        "dayofweek",
        "is_holiday",
        "hour_sin",
        "hour_cos",
        "day_sin",
        "day_cos"
    ],
    "error_metrics": {
        "2025-11-26T00:00:00+00:00": {
            "solar_50hz": {
                "mse": 183673.68172315575,
                "rmse": 428.57167629599104,
                "mae": 171.79086311265826,
                "mape": 2977694079277.5024,
                "smape": 280.0991918261305,
                "bias": -134.93092530119264,
                "variance": 165467.32712051974,
                "std": 406.7767534170552,
                "r2": 0.8565773413118142,
                "prediction_interval_coverage": 0.7916666666666666,
                "prediction_interval_width": 279.90844089496494
            }
        },
        "2025-12-03T00:00:00+00:00": {
            "solar_50hz": {
                "mse": 102587.19853073808,
                "rmse": 320.2923641467871,
                "mae": 130.39578974695021,
                "mape": 4541023141471.021,
                "smape": 288.3189174916618,
                "bias": -37.978203327555754,
                "variance": 101144.85460274892,
                "std": 318.0327885655014,
                "r2": 0.8716087890461077,
                "prediction_interval_coverage": 0.7797619047619048,
                "prediction_interval_width": 279.90844089496494
            }
        },
        "2025-12-10T00:00:00+00:00": {
            "solar_50hz": {
                "mse": 243551.13056293342,
                "rmse": 493.50899744881394,
                "mae": 199.91136764567347,
                "mape": 4579471294126.551,
                "smape": 290.1299449134208,
                "bias": -159.77361572378967,
                "variance": 218023.5222814802,
                "std": 466.9298901135803,
                "r2": 0.8430281231454947,
                "prediction_interval_coverage": 0.7857142857142857,
                "prediction_interval_width": 279.90844089496494
            }
        },
        "2025-12-17T00:00:00+00:00": {
            "solar_50hz": {
                "mse": 114821.53696104411,
                "rmse": 338.85326759682295,
                "mae": 139.34613992192206,
                "mape": 3774430860569.415,
                "smape": 288.85472370502214,
                "bias": -60.86631130972778,
                "variance": 111116.82910859144,
                "std": 333.34191021920935,
                "r2": 0.8886049390378775,
                "prediction_interval_coverage": 0.7738095238095238,
                "prediction_interval_width": 279.90844089496494
            }
        },
        "2025-12-24T00:00:00+00:00": {
            "solar_50hz": {
                "mse": 320205.386777586,
                "rmse": 565.8669338082815,
                "mae": 255.95560248193337,
                "mape": 5646871003853.012,
                "smape": 297.5932782935734,
                "bias": -236.1585784913816,
                "variance": 264434.51258251595,
                "std": 514.2319637892183,
                "r2": 0.7941337008979413,
                "prediction_interval_coverage": 0.7440476190476191,
                "prediction_interval_width": 279.9084408949649
            }
        }
    }
}