{
    "start_date": "2023-03-21T00:00:00+00:00",
    "end_date": "2025-02-17T23:00:00+00:00",
    "horizon": 168,
    "features": [
        "temperature_2m_agg",
        "relative_humidity_2m_agg",
        "wind_speed_10m_agg",
        "wind_speed_100m_agg",
        "wind_direction_10m_agg",
        "wind_direction_100m_agg",
        "wind_gusts_10m_agg",
        "shortwave_radiation_agg",
        "direct_radiation_agg",
        "diffuse_radiation_agg",
        "direct_normal_irradiance_agg",
        "global_tilted_irradiance_agg",
        "terrestrial_radiation_agg",
        "dew_point_temperature_agg",
        "dew_point_spread_agg",
        "wind_chill_agg",
        "humidex_agg",
        "pressure_trend_agg",
        "rain_indicator_agg",
        "wind_speed_gradient_agg",
        "wind_u_agg",
        "wind_v_agg",
        "cloud_cover_fraction_agg",
        "effective_solar_agg",
        "precip_lags_lag_1_agg",
        "precip_lags_lag_3_agg",
        "temp_roll_6_agg",
        "temp_roll_12_agg",
        "temp_roll_24_agg",
        "wind_offshore_50hz",
        "wind_offshore_tenn",
        "wind_onshore_ampr",
        "wind_onshore_50hz",
        "wind_onshore_tenn",
        "wind_onshore_tran",
        "solar_ampr",
        "solar_50hz",
        "solar_tenn",
        "solar_tran",
        "hour",
        "dayofweek",
        "is_holiday",
        "hour_sin",
        "hour_cos",
        "day_sin",
        "day_cos"
    ],
    "error_metrics": {
        "2025-01-14T00:00:00+00:00": {
            "load_ampr": {
                "mse": 419160.0368421273,
                "rmse": 647.4256998622524,
                "mae": 487.9982697549659,
                "mape": 2.227206709832514,
                "smape": 4.478928226875013,
                "bias": -130.70490889520207,
                "variance": 402076.2636328242,
                "std": 634.0948380430361,
                "r2": 0.9548378372590136,
                "prediction_interval_coverage": 0.8095238095238095,
                "prediction_interval_width": 1634.0399466115928
            }
        },
        "2025-01-21T00:00:00+00:00": {
            "load_ampr": {
                "mse": 499650.6969355044,
                "rmse": 706.8597434678993,
                "mae": 563.4459715446259,
                "mape": 2.7678933631502494,
                "smape": 5.625262563118155,
                "bias": -256.41085870443254,
                "variance": 433904.16847396,
                "std": 658.7140263224702,
                "r2": 0.9428825860501309,
                "prediction_interval_coverage": 0.7440476190476191,
                "prediction_interval_width": 1634.0399466115928
            }
        },
        "2025-01-28T00:00:00+00:00": {
            "load_ampr": {
                "mse": 1059315.243887442,
                "rmse": 1029.2304134096707,
                "mae": 723.3927536914046,
                "mape": 3.5238793111286686,
                "smape": 7.296142016965164,
                "bias": -539.6585729374539,
                "variance": 768083.8685425529,
                "std": 876.4039414234471,
                "r2": 0.861158668516001,
                "prediction_interval_coverage": 0.7023809523809523,
                "prediction_interval_width": 1634.0399466115928
            }
        },
        "2025-02-04T00:00:00+00:00": {
            "load_ampr": {
                "mse": 1148222.4501248705,
                "rmse": 1071.5514220628288,
                "mae": 879.800403859687,
                "mape": 3.972687581284859,
                "smape": 8.158454558018617,
                "bias": -723.5544581540768,
                "variance": 624691.3962102305,
                "std": 790.3742127690089,
                "r2": 0.8749915511115115,
                "prediction_interval_coverage": 0.5238095238095238,
                "prediction_interval_width": 1634.0399466115923
            }
        },
        "2025-02-11T00:00:00+00:00": {
            "load_ampr": {
                "mse": 1664957.0769252095,
                "rmse": 1290.3321575955586,
                "mae": 1134.7480589278302,
                "mape": 5.150288246766296,
                "smape": 10.651432984496708,
                "bias": -1117.476514810839,
                "variance": 416203.31577143073,
                "std": 645.1382144714656,
                "r2": 0.8154128180196909,
                "prediction_interval_coverage": 0.34523809523809523,
                "prediction_interval_width": 1634.039946611593
            }
        }
    }
}