{
    "start_date": "2023-03-15T00:00:00+00:00",
    "end_date": "2025-02-11T23:00:00+00:00",
    "horizon": 168,
    "features": [
        "temperature_2m_city_munich",
        "precipitation_city_munich",
        "cloud_cover_city_munich",
        "wind_speed_10m_city_munich",
        "wind_speed_100m_city_munich",
        "shortwave_radiation_city_munich",
        "temperature_2m_city_bremen",
        "precipitation_city_bremen",
        "cloud_cover_city_bremen",
        "wind_speed_10m_city_bremen",
        "wind_speed_100m_city_bremen",
        "shortwave_radiation_city_bremen",
        "temperature_2m_city_kiel",
        "precipitation_city_kiel",
        "cloud_cover_city_kiel",
        "wind_speed_10m_city_kiel",
        "wind_speed_100m_city_kiel",
        "shortwave_radiation_city_kiel",
        "temperature_2m_city_kassel",
        "precipitation_city_kassel",
        "cloud_cover_city_kassel",
        "wind_speed_10m_city_kassel",
        "wind_speed_100m_city_kassel",
        "shortwave_radiation_city_kassel",
        "temperature_2m_city_bremerhaven",
        "precipitation_city_bremerhaven",
        "cloud_cover_city_bremerhaven",
        "wind_speed_10m_city_bremerhaven",
        "wind_speed_100m_city_bremerhaven",
        "shortwave_radiation_city_bremerhaven",
        "wind_offshore_50hz",
        "wind_offshore_tenn",
        "wind_onshore_ampr",
        "wind_onshore_50hz",
        "wind_onshore_tenn",
        "wind_onshore_tran",
        "solar_ampr",
        "solar_50hz",
        "solar_tenn",
        "solar_tran",
        "load_ampr",
        "load_50hz",
        "load_tenn",
        "load_tran",
        "residual_load_ampr",
        "residual_load_50hz",
        "residual_load_tenn",
        "residual_load_tran",
        "hour",
        "dayofweek",
        "is_holiday",
        "hour_sin",
        "hour_cos",
        "day_sin",
        "day_cos"
    ],
    "error_metrics": {
        "2025-01-08T00:00:00+00:00": {
            "biomass_tenn": {
                "mse": 3484.4239738519086,
                "rmse": 59.029009595722584,
                "mae": 49.820464663811784,
                "mape": 2.557816730180024,
                "smape": 5.119368692891785,
                "bias": -8.667425149825618,
                "variance": 3409.299715124079,
                "std": 58.38920889277469,
                "r2": 0.2808373101344136,
                "prediction_interval_coverage": 0.0,
                "prediction_interval_width": 0.0
            },
            "gas_tenn": {
                "mse": 4013713.2131807846,
                "rmse": 2003.425370005278,
                "mae": 1778.8121646247857,
                "mape": 48.503991977921366,
                "smape": 133.18562595214937,
                "bias": -1778.8121646247857,
                "variance": 849540.4961636683,
                "std": 921.7052110971644,
                "r2": -3.0209588109138172,
                "prediction_interval_coverage": 0.0,
                "prediction_interval_width": 0.0
            },
            "hard_coal_tenn": {
                "mse": 236961.55185752592,
                "rmse": 486.7869676331998,
                "mae": 415.0113568018485,
                "mape": 39.285845959277445,
                "smape": 83.25680672693426,
                "bias": -290.79214167573116,
                "variance": 152401.4821971674,
                "std": 390.3863242957768,
                "r2": -0.4611681743161524,
                "prediction_interval_coverage": 0.0,
                "prediction_interval_width": 0.0
            },
            "oil_tenn": {
                "mse": 516.4746171339409,
                "rmse": 22.726077909176077,
                "mae": 8.90377646124239,
                "mape": 1400981281606.893,
                "smape": 390.8405496006629,
                "bias": -6.091016604010027,
                "variance": 479.37413386361504,
                "std": 21.894614266152647,
                "r2": -0.07739358603124202,
                "prediction_interval_coverage": 0.0,
                "prediction_interval_width": 0.0
            },
            "renewables_tenn": {
                "mse": 289877.40258627397,
                "rmse": 538.4026398396222,
                "mae": 501.12112886416867,
                "mape": 69.68054970964818,
                "smape": 98.18734229176593,
                "bias": 411.3436403508772,
                "variance": 120673.81212916214,
                "std": 347.3813641074635,
                "r2": -1.363514803301658,
                "prediction_interval_coverage": 0.0,
                "prediction_interval_width": 0.0
            },
            "waste_tenn": {
                "mse": 2941.709142279257,
                "rmse": 54.23752522266532,
                "mae": 45.768450143215176,
                "mape": 22.473647831987588,
                "smape": 38.55824657989135,
                "bias": 43.44785401002506,
                "variance": 1053.993124202806,
                "std": 32.465260266980856,
                "r2": -1.7910135984086577,
                "prediction_interval_coverage": 0.0,
                "prediction_interval_width": 0.0
            }
        },
        "2025-01-15T00:00:00+00:00": {
            "biomass_tenn": {
                "mse": 3452.677392431605,
                "rmse": 58.759487680132175,
                "mae": 48.19188844197988,
                "mape": 2.446429162349258,
                "smape": 4.921573763904295,
                "bias": -14.765375669701474,
                "variance": 3234.661073764193,
                "std": 56.87408086082968,
                "r2": 0.14916673750487042,
                "prediction_interval_coverage": 0.0,
                "prediction_interval_width": 0.0
            },
            "gas_tenn": {
                "mse": 7668353.564297112,
                "rmse": 2769.1792221337196,
                "mae": 2706.8163662412057,
                "mape": 60.69811153953238,
                "smape": 175.30294107694294,
                "bias": -2706.8163662412057,
                "variance": 341498.7237458668,
                "std": 584.378921373681,
                "r2": -16.630509222935938,
                "prediction_interval_coverage": 0.0,
                "prediction_interval_width": 0.0
            },
            "hard_coal_tenn": {
                "mse": 234061.83539133004,
                "rmse": 483.7993751456589,
                "mae": 430.18391676144427,
                "mape": 34.70424406009554,
                "smape": 80.15859744059118,
                "bias": -386.9225516665821,
                "variance": 84352.77440315118,
                "std": 290.43549094962754,
                "r2": -1.527011493998525,
                "prediction_interval_coverage": 0.0,
                "prediction_interval_width": 0.0
            },
            "oil_tenn": {
                "mse": 146.8462728112403,
                "rmse": 12.11801439226907,
                "mae": 4.66156705006564,
                "mape": 1500976515346.1377,
                "smape": 381.71707230259256,
                "bias": -1.6508223684210523,
                "variance": 144.12105831916102,
                "std": 12.005043036955804,
                "r2": -0.018909203997407475,
                "prediction_interval_coverage": 0.0,
                "prediction_interval_width": 0.0
            },
            "renewables_tenn": {
                "mse": 180095.69594173622,
                "rmse": 424.37683247526155,
                "mae": 374.54866300757203,
                "mape": 37.231691270079914,
                "smape": 63.19344016286189,
                "bias": 120.9546365914787,
                "variance": 165465.67182875957,
                "std": 406.7747187679681,
                "r2": -0.019738285062737226,
                "prediction_interval_coverage": 0.0,
                "prediction_interval_width": 0.0
            },
            "waste_tenn": {
                "mse": 11326.226646686317,
                "rmse": 106.4247464017947,
                "mae": 99.91036967418549,
                "mape": 75.74037833780244,
                "smape": 95.45194381813403,
                "bias": 99.91036967418549,
                "variance": 1344.1446782539138,
                "std": 36.66257871800501,
                "r2": -7.426344894211418,
                "prediction_interval_coverage": 0.0,
                "prediction_interval_width": 0.0
            }
        },
        "2025-01-22T00:00:00+00:00": {
            "biomass_tenn": {
                "mse": 4964.252816851124,
                "rmse": 70.45745394811769,
                "mae": 61.1317251481467,
                "mape": 3.0772646626413125,
                "smape": 6.226472950545841,
                "bias": -30.932785733656807,
                "variance": 4007.4155836068016,
                "std": 63.30415139314958,
                "r2": 0.01595674232856048,
                "prediction_interval_coverage": 0.0,
                "prediction_interval_width": 0.0
            },
            "gas_tenn": {
                "mse": 2250621.0084669148,
                "rmse": 1500.2069885408862,
                "mae": 1048.7805318898436,
                "mape": 34.89542102312211,
                "smape": 85.37235134284758,
                "bias": -846.2202102245293,
                "variance": 1534532.3642744678,
                "std": 1238.7624325408274,
                "r2": -0.26738022025675057,
                "prediction_interval_coverage": 0.0,
                "prediction_interval_width": 0.0
            },
            "hard_coal_tenn": {
                "mse": 209313.5534074066,
                "rmse": 457.50798179639077,
                "mae": 387.38262077924014,
                "mape": 57.572255402791704,
                "smape": 95.41800222308856,
                "bias": -97.91018791157354,
                "variance": 199727.14851052695,
                "std": 446.9084341456614,
                "r2": 0.05016485778552637,
                "prediction_interval_coverage": 0.0,
                "prediction_interval_width": 0.0
            },
            "oil_tenn": {
                "mse": 412.0365069725265,
                "rmse": 20.298682394986294,
                "mae": 6.857420243316625,
                "mape": 1597969817970.2725,
                "smape": 393.5931303843569,
                "bias": -3.6132910401002505,
                "variance": 398.9806348320579,
                "std": 19.97449961405937,
                "r2": -0.03272307225127413,
                "prediction_interval_coverage": 0.0,
                "prediction_interval_width": 0.0
            },
            "renewables_tenn": {
                "mse": 354721.351112223,
                "rmse": 595.5848815342973,
                "mae": 547.7747311268391,
                "mape": 89.13787445507586,
                "smape": 113.2197849339376,
                "bias": 509.1135181704262,
                "variance": 95524.77672835423,
                "std": 309.0708280125354,
                "r2": -2.5859390033064873,
                "prediction_interval_coverage": 0.0,
                "prediction_interval_width": 0.0
            },
            "waste_tenn": {
                "mse": 6674.021510911077,
                "rmse": 81.69468471639435,
                "mae": 80.93543233082707,
                "mape": 43.92008832087447,
                "smape": 71.587686713156,
                "bias": 80.93543233082707,
                "variance": 123.47730433319161,
                "std": 11.112034212203975,
                "r2": -53.05059291626478,
                "prediction_interval_coverage": 0.0,
                "prediction_interval_width": 0.0
            }
        },
        "2025-01-29T00:00:00+00:00": {
            "biomass_tenn": {
                "mse": 3352.491056227256,
                "rmse": 57.90069996318918,
                "mae": 44.72008761913663,
                "mape": 2.3117227250634578,
                "smape": 4.623291271566308,
                "bias": -2.11581737861355,
                "variance": 3348.014373047613,
                "std": 57.8620287671251,
                "r2": 0.1299379910426437,
                "prediction_interval_coverage": 0.0,
                "prediction_interval_width": 0.0
            },
            "gas_tenn": {
                "mse": 3320972.183276827,
                "rmse": 1822.3534737467446,
                "mae": 1554.7970111097916,
                "mape": 41.86492248074649,
                "smape": 111.7606555631792,
                "bias": -1546.5946790231485,
                "variance": 929017.0820941111,
                "std": 963.8553221796885,
                "r2": -1.6824276296215164,
                "prediction_interval_coverage": 0.0,
                "prediction_interval_width": 0.0
            },
            "hard_coal_tenn": {
                "mse": 341535.1979880263,
                "rmse": 584.410128238745,
                "mae": 532.4592524906584,
                "mape": 39.386311746395705,
                "smape": 95.75354400398949,
                "bias": -506.60365175900637,
                "variance": 84887.93801246562,
                "std": 291.35534663442445,
                "r2": -2.594084774794098,
                "prediction_interval_coverage": 0.0,
                "prediction_interval_width": 0.0
            },
            "oil_tenn": {
                "mse": 3.230180072393252,
                "rmse": 1.7972701723428373,
                "mae": 1.789317042606516,
                "mape": 1736003078871.1548,
                "smape": 389.9683339857289,
                "bias": 1.789317042606516,
                "variance": 0.028524593431122458,
                "std": 0.1688922539109549,
                "r2": -112.2419320960026,
                "prediction_interval_coverage": 0.0,
                "prediction_interval_width": 0.0
            },
            "renewables_tenn": {
                "mse": 293643.80923603766,
                "rmse": 541.889111568075,
                "mae": 504.4286638742294,
                "mape": 70.75381104706916,
                "smape": 99.09858574113115,
                "bias": 411.9391290726817,
                "variance": 123949.96317487815,
                "std": 352.0652825469705,
                "r2": -1.291647446778203,
                "prediction_interval_coverage": 0.0,
                "prediction_interval_width": 0.0
            },
            "waste_tenn": {
                "mse": 15180.873120309589,
                "rmse": 123.2106859014655,
                "mae": 120.22252506265667,
                "mape": 87.2408561225876,
                "smape": 118.36788393986477,
                "bias": 120.22252506265667,
                "variance": 727.4175878684807,
                "std": 26.97068015212966,
                "r2": -19.869543675447034,
                "prediction_interval_coverage": 0.0,
                "prediction_interval_width": 0.0
            }
        },
        "2025-02-05T00:00:00+00:00": {
            "biomass_tenn": {
                "mse": 3407.5575940607814,
                "rmse": 58.374288809892846,
                "mae": 45.286374358520455,
                "mape": 2.344050520601194,
                "smape": 4.68552994523591,
                "bias": 1.3597550947172903,
                "variance": 3405.708660143172,
                "std": 58.358449775016915,
                "r2": 0.06772840298736371,
                "prediction_interval_coverage": 0.0,
                "prediction_interval_width": 0.0
            },
            "gas_tenn": {
                "mse": 3127262.8150661727,
                "rmse": 1768.4068578995539,
                "mae": 1470.9580680757579,
                "mape": 39.67017001675112,
                "smape": 105.4324409826363,
                "bias": -1470.9580680757579,
                "variance": 963545.1770290069,
                "std": 981.6033705265111,
                "r2": -1.5488923028907085,
                "prediction_interval_coverage": 0.0,
                "prediction_interval_width": 0.0
            },
            "hard_coal_tenn": {
                "mse": 158391.8448688744,
                "rmse": 397.98472944181464,
                "mae": 309.1603721369125,
                "mape": 38.45873729971605,
                "smape": 69.46817864339445,
                "bias": -105.64344348344267,
                "variance": 147231.30771783506,
                "std": 383.7073203860399,
                "r2": 0.10486272714538636,
                "prediction_interval_coverage": 0.0,
                "prediction_interval_width": 0.0
            },
            "oil_tenn": {
                "mse": 3.314065121489502,
                "rmse": 1.8204573934837096,
                "mae": 1.8204573934837092,
                "mape": 1820461435620.1116,
                "smape": 400.0,
                "bias": 1.8204573934837092,
                "variance": 4.930380657631324e-32,
                "std": 2.220446049250313e-16,
                "r2": 0.0,
                "prediction_interval_coverage": 0.0,
                "prediction_interval_width": 0.0
            },
            "renewables_tenn": {
                "mse": 313576.3560648983,
                "rmse": 559.9788889457336,
                "mae": 520.2649222035122,
                "mape": 77.77840722242301,
                "smape": 104.86043239412687,
                "bias": 466.0557174185463,
                "variance": 96368.42432638237,
                "std": 310.4326405621393,
                "r2": -2.1389399993816034,
                "prediction_interval_coverage": 0.0,
                "prediction_interval_width": 0.0
            },
            "waste_tenn": {
                "mse": 12345.289101892406,
                "rmse": 111.10935650021742,
                "mae": 108.58344485823706,
                "mape": 73.65776824705466,
                "smape": 104.27900379352279,
                "bias": 108.58344485823706,
                "variance": 554.9246046105956,
                "std": 23.55683774640806,
                "r2": -21.30711977652039,
                "prediction_interval_coverage": 0.0,
                "prediction_interval_width": 0.0
            }
        }
    }
}