{
    "start_date": "2023-12-24T00:00:00+00:00",
    "end_date": "2025-11-22T23:00:00+00:00",
    "horizon": 168,
    "features": [
        "temperature_2m_agg",
        "relative_humidity_2m_agg",
        "surface_pressure_agg",
        "precipitation_agg",
        "cloud_cover_agg",
        "wind_speed_10m_agg",
        "wind_speed_100m_agg",
        "wind_direction_10m_agg",
        "wind_gusts_10m_agg",
        "air_density_agg",
        "wind_power_density_agg",
        "wind_dir_sin_agg",
        "wind_dir_cos_agg",
        "turbulence_intensity_agg",
        "gust_factor_agg",
        "vapor_pressure_agg",
        "wind_speed_lag_1_agg",
        "wind_speed_lag_6_agg",
        "wind_speed_lag_12_agg",
        "precip_lag_1_agg",
        "precip_lag_6_agg",
        "hour",
        "dayofweek",
        "is_holiday",
        "hour_sin",
        "hour_cos",
        "day_sin",
        "day_cos"
    ],
    "error_metrics": {
        "2025-10-19T00:00:00+00:00": {
            "wind_onshore_ampr": {
                "mse": 1984628.282074675,
                "rmse": 1408.7683564286483,
                "mae": 1216.6496408412231,
                "mape": 33.352317914292506,
                "smape": 52.67603820360277,
                "bias": -659.0388903472298,
                "variance": 1550296.0230845672,
                "std": 1245.1088398548004,
                "r2": 0.7559039818923987,
                "prediction_interval_coverage": 0.8571428571428571,
                "prediction_interval_width": 3807.5543045640807
            }
        },
        "2025-10-26T00:00:00+00:00": {
            "wind_onshore_ampr": {
                "mse": 2899784.2470670063,
                "rmse": 1702.8752881720395,
                "mae": 1487.205459367935,
                "mape": 25.552502344341526,
                "smape": 53.49323362710903,
                "bias": -1117.7327932744931,
                "variance": 1650457.649905805,
                "std": 1284.701385500072,
                "r2": 0.5124241949021933,
                "prediction_interval_coverage": 0.6785714285714286,
                "prediction_interval_width": 3808.4517161398217
            }
        },
        "2025-11-02T00:00:00+00:00": {
            "wind_onshore_ampr": {
                "mse": 782717.6116494637,
                "rmse": 884.7132934739161,
                "mae": 725.880399900725,
                "mape": 96.84962239212244,
                "smape": 91.72007608265696,
                "bias": -197.93716693033846,
                "variance": 743538.4895970551,
                "std": 862.2867792080864,
                "r2": 0.800426972146479,
                "prediction_interval_coverage": 0.9702380952380952,
                "prediction_interval_width": 3807.423360462384
            }
        },
        "2025-11-09T00:00:00+00:00": {
            "wind_onshore_ampr": {
                "mse": 1415808.285885891,
                "rmse": 1189.8774247315944,
                "mae": 920.2962370377351,
                "mape": 39.73516545746631,
                "smape": 79.99803615827994,
                "bias": -487.97116237216636,
                "variance": 1177692.4305790479,
                "std": 1085.2153844187096,
                "r2": 0.6112380640523714,
                "prediction_interval_coverage": 0.8869047619047619,
                "prediction_interval_width": 3808.3788623962423
            }
        },
        "2025-11-16T00:00:00+00:00": {
            "wind_onshore_ampr": {
                "mse": 622003.370930175,
                "rmse": 788.6719032209623,
                "mae": 662.1943850130823,
                "mape": 85.98169385656816,
                "smape": 91.77257824524881,
                "bias": 59.379529912215034,
                "variance": 618477.4423575794,
                "std": 786.4333680341771,
                "r2": 0.7691984443713229,
                "prediction_interval_coverage": 0.9880952380952381,
                "prediction_interval_width": 3807.8940858256633
            }
        }
    }
}