{
    "start_date": "2023-05-28T00:00:00+00:00",
    "end_date": "2025-04-26T23:00:00+00:00",
    "horizon": 168,
    "features": [
        "temperature_2m_agg",
        "relative_humidity_2m_agg",
        "surface_pressure_agg",
        "precipitation_agg",
        "cloud_cover_agg",
        "shortwave_radiation_agg",
        "direct_radiation_agg",
        "diffuse_radiation_agg",
        "direct_normal_irradiance_agg",
        "global_tilted_irradiance_agg",
        "terrestrial_radiation_agg",
        "cloud_cover_fraction_agg",
        "clear_sky_fraction_agg",
        "air_density_moist_agg",
        "diffuse_ratio_agg",
        "cloud_lag_1_agg",
        "cloud_lag_3_agg",
        "cloud_lag_6_agg",
        "cloud_lag_12_agg",
        "shortwave_lag_1_agg",
        "shortwave_lag_3_agg",
        "shortwave_lag_6_agg",
        "shortwave_lag_12_agg",
        "solar_elevation_deg_sol_cestas",
        "solar_azimuth_deg_sol_cestas",
        "solar_elevation_deg_sol_athies",
        "solar_azimuth_deg_sol_athies",
        "solar_elevation_deg_sol_toul",
        "solar_azimuth_deg_sol_toul",
        "solar_elevation_deg_sol_gabardan",
        "solar_azimuth_deg_sol_gabardan",
        "hour",
        "dayofweek",
        "is_holiday",
        "hour_sin",
        "hour_cos",
        "day_sin",
        "day_cos"
    ],
    "error_metrics": {
        "2025-03-23T00:00:00+00:00": {
            "solar_rte": {
                "mse": 479548.53155679326,
                "rmse": 692.4944270943942,
                "mae": 410.84621576363014,
                "mape": 3698107233717.0737,
                "smape": 181.39558811719562,
                "bias": -85.74096770088653,
                "variance": 472197.01801450877,
                "std": 687.1659319367549,
                "r2": 0.975058187282144,
                "prediction_interval_coverage": 0.7380952380952381,
                "prediction_interval_width": 1134.3361813826618
            }
        },
        "2025-03-30T00:00:00+00:00": {
            "solar_rte": {
                "mse": 1459589.213756306,
                "rmse": 1208.1346008439234,
                "mae": 629.2293184001375,
                "mape": 1082079514626.4045,
                "smape": 173.56718204343494,
                "bias": -24.95029284149762,
                "variance": 1458966.6966434296,
                "std": 1207.8769377065817,
                "r2": 0.9280009272341246,
                "prediction_interval_coverage": 0.7083333333333334,
                "prediction_interval_width": 1134.3361813826618
            }
        },
        "2025-04-06T00:00:00+00:00": {
            "solar_rte": {
                "mse": 596274.4017168533,
                "rmse": 772.1880611074308,
                "mae": 453.1099008769015,
                "mape": 1947908477853.4187,
                "smape": 158.7375259534075,
                "bias": -238.79105055637078,
                "variance": 539253.235891038,
                "std": 734.3386384298718,
                "r2": 0.9761959953101291,
                "prediction_interval_coverage": 0.7023809523809523,
                "prediction_interval_width": 1134.3361813826618
            }
        },
        "2025-04-13T00:00:00+00:00": {
            "solar_rte": {
                "mse": 852982.8837661477,
                "rmse": 923.5707248316978,
                "mae": 489.95310297813177,
                "mape": 2723634394598.85,
                "smape": 163.07912471282907,
                "bias": -74.06287941975636,
                "variance": 847497.5736582024,
                "std": 920.5963141671829,
                "r2": 0.942729675169093,
                "prediction_interval_coverage": 0.7380952380952381,
                "prediction_interval_width": 1134.3361813826618
            }
        },
        "2025-04-20T00:00:00+00:00": {
            "solar_rte": {
                "mse": 1262747.337342767,
                "rmse": 1123.72031099503,
                "mae": 655.4300109100916,
                "mape": 2426648710602.728,
                "smape": 158.4445710648762,
                "bias": -449.7147210709994,
                "variance": 1060504.0069948002,
                "std": 1029.8077524445036,
                "r2": 0.9248342082897587,
                "prediction_interval_coverage": 0.6309523809523809,
                "prediction_interval_width": 1134.3361813826618
            }
        }
    }
}